{
    "Meta": {
        "Name": "Lostmail_vs_Dzage",
        "Event": "TFC_2"
    },
    "Lostmail": {
        "Strikes Landed": 14,
        "Strikes Thrown": 28,
        "Strikes Absorbed": 10,
        "Accuracy": 50.0,
        "Knockdowns": 1,
        "Striking Differential": 4,
        "Takedowns Finished": 0,
        "Takedowns Attempted": 2,
        "Takedown Accuracy": 0.0,
        "Takedowns Defended": 0,
        "Times Taken Down": 0,
        "Takedown Defense Rate": 0.0,
        "Submissions Attempted": 0
    },
    "Dzage": {
        "Strikes Landed": 10,
        "Strikes Thrown": 27,
        "Strikes Absorbed": 14,
        "Accuracy": 37.0,
        "Knockdowns": 0,
        "Striking Differential": -4,
        "Takedowns Finished": 0,
        "Takedowns Attempted": 0,
        "Takedown Accuracy": 0.0,
        "Takedowns Defended": 2,
        "Times Taken Down": 0,
        "Takedown Defense Rate": 100.0,
        "Submissions Attempted": 0
    },
    "Result": "dzage via decision."
}